<?xml version="1.0" encoding="UTF-8" standalone="yes"?>
<record:record xmlns:address="http://www.orcid.org/ns/address" xmlns:email="http://www.orcid.org/ns/email" xmlns:history="http://www.orcid.org/ns/history" xmlns:employment="http://www.orcid.org/ns/employment" xmlns:education="http://www.orcid.org/ns/education" xmlns:other-name="http://www.orcid.org/ns/other-name" xmlns:deprecated="http://www.orcid.org/ns/deprecated" xmlns:funding="http://www.orcid.org/ns/funding" xmlns:research-resource="http://www.orcid.org/ns/research-resource" xmlns:service="http://www.orcid.org/ns/service" xmlns:researcher-url="http://www.orcid.org/ns/researcher-url" xmlns:distinction="http://www.orcid.org/ns/distinction" xmlns:internal="http://www.orcid.org/ns/internal" xmlns:membership="http://www.orcid.org/ns/membership" xmlns:person="http://www.orcid.org/ns/person" xmlns:personal-details="http://www.orcid.org/ns/personal-details" xmlns:bulk="http://www.orcid.org/ns/bulk" xmlns:common="http://www.orcid.org/ns/common" xmlns:record="http://www.orcid.org/ns/record" xmlns:keyword="http://www.orcid.org/ns/keyword" xmlns:activities="http://www.orcid.org/ns/activities" xmlns:qualification="http://www.orcid.org/ns/qualification" xmlns:external-identifier="http://www.orcid.org/ns/external-identifier" xmlns:error="http://www.orcid.org/ns/error" xmlns:preferences="http://www.orcid.org/ns/preferences" xmlns:invited-position="http://www.orcid.org/ns/invited-position" xmlns:work="http://www.orcid.org/ns/work" xmlns:peer-review="http://www.orcid.org/ns/peer-review" path="/0000-0002-9545-1191">
    <common:orcid-identifier>
        <common:uri>https://orcid.org/0000-0002-9545-1191</common:uri>
        <common:path>0000-0002-9545-1191</common:path>
        <common:host>orcid.org</common:host>
    </common:orcid-identifier>
    <preferences:preferences>
        <preferences:locale>zh_TW</preferences:locale>
    </preferences:preferences>
    <history:history>
        <history:creation-method>Member-referred</history:creation-method>
        <history:submission-date>2014-07-17T13:25:31.971Z</history:submission-date>
        <common:last-modified-date>2018-02-05T23:27:44.543Z</common:last-modified-date>
        <history:claimed>true</history:claimed>
        <history:verified-email>true</history:verified-email>
        <history:verified-primary-email>true</history:verified-primary-email>
    </history:history>
    <person:person path="/0000-0002-9545-1191/person">
        <common:last-modified-date>2018-02-05T23:27:36.636Z</common:last-modified-date>
        <person:name visibility="public" path="0000-0002-9545-1191">
            <common:created-date>2016-04-15T23:22:11.230Z</common:created-date>
            <common:last-modified-date>2016-04-15T23:22:11.230Z</common:last-modified-date>
            <personal-details:given-names>Yi-Fong</personal-details:given-names>
            <personal-details:family-name>Chen</personal-details:family-name>
        </person:name>
        <other-name:other-names path="/0000-0002-9545-1191/other-names"/>
        <person:biography visibility="public" path="/0000-0002-9545-1191/biography">
            <common:created-date>2016-04-15T23:22:11.232Z</common:created-date>
            <common:last-modified-date>2016-04-15T23:22:11.232Z</common:last-modified-date>
            <personal-details:content>Yi-Fong Chen received his B.S. degrees in Pharmaceutical Science from Chia Nan University of Pharmacy and Science (2010). He received Ph.D. degrees in the Ph.D. Program for Cancer Biology and Drug Discovery, China Medical University and Academia Sinica, Taichung, Taiwan 40402, R.O.C. (2015). His research interests include the design and synthesis of bioactive compounds, medicinal chemistry of lead development for anti-cancer activity.</personal-details:content>
        </person:biography>
        <researcher-url:researcher-urls path="/0000-0002-9545-1191/researcher-urls"/>
        <email:emails path="/0000-0002-9545-1191/email"/>
        <address:addresses path="/0000-0002-9545-1191/address">
            <common:last-modified-date>2016-06-06T15:29:36.952Z</common:last-modified-date>
            <address:address put-code="84545" visibility="public" path="/0000-0002-9545-1191/address/84545" display-index="0">
                <common:created-date>2016-01-24T18:10:21.710Z</common:created-date>
                <common:last-modified-date>2016-06-06T15:29:36.952Z</common:last-modified-date>
                <common:source>
                    <common:source-orcid>
                        <common:uri>https://orcid.org/0000-0002-9545-1191</common:uri>
                        <common:path>0000-0002-9545-1191</common:path>
                        <common:host>orcid.org</common:host>
                    </common:source-orcid>
                    <common:source-name>Yi-Fong Chen</common:source-name>
                </common:source>
                <address:country>TW</address:country>
            </address:address>
        </address:addresses>
        <keyword:keywords path="/0000-0002-9545-1191/keywords">
            <common:last-modified-date>2014-07-17T13:49:42.710Z</common:last-modified-date>
            <keyword:keyword put-code="165242" visibility="public" path="/0000-0002-9545-1191/keywords/165242" display-index="0">
                <common:created-date>2014-07-17T13:48:29.167Z</common:created-date>
                <common:last-modified-date>2014-07-17T13:48:29.167Z</common:last-modified-date>
                <common:source>
                    <common:source-orcid>
                        <common:uri>https://orcid.org/0000-0002-9545-1191</common:uri>
                        <common:path>0000-0002-9545-1191</common:path>
                        <common:host>orcid.org</common:host>
                    </common:source-orcid>
                    <common:source-name>Yi-Fong Chen</common:source-name>
                </common:source>
                <keyword:content>Medicinal Chemistry</keyword:content>
            </keyword:keyword>
            <keyword:keyword put-code="165243" visibility="public" path="/0000-0002-9545-1191/keywords/165243" display-index="0">
                <common:created-date>2014-07-17T13:49:42.705Z</common:created-date>
                <common:last-modified-date>2014-07-17T13:49:42.705Z</common:last-modified-date>
                <common:source>
                    <common:source-orcid>
                        <common:uri>https://orcid.org/0000-0002-9545-1191</common:uri>
                        <common:path>0000-0002-9545-1191</common:path>
                        <common:host>orcid.org</common:host>
                    </common:source-orcid>
                    <common:source-name>Yi-Fong Chen</common:source-name>
                </common:source>
                <keyword:content>Lead Drug Development</keyword:content>
            </keyword:keyword>
            <keyword:keyword put-code="165244" visibility="public" path="/0000-0002-9545-1191/keywords/165244" display-index="0">
                <common:created-date>2014-07-17T13:49:42.710Z</common:created-date>
                <common:last-modified-date>2014-07-17T13:49:42.710Z</common:last-modified-date>
                <common:source>
                    <common:source-orcid>
                        <common:uri>https://orcid.org/0000-0002-9545-1191</common:uri>
                        <common:path>0000-0002-9545-1191</common:path>
                        <common:host>orcid.org</common:host>
                    </common:source-orcid>
                    <common:source-name>Yi-Fong Chen</common:source-name>
                </common:source>
                <keyword:content>Organic Synthesis</keyword:content>
            </keyword:keyword>
        </keyword:keywords>
        <external-identifier:external-identifiers path="/0000-0002-9545-1191/external-identifiers">
            <common:last-modified-date>2018-02-05T23:27:36.636Z</common:last-modified-date>
            <external-identifier:external-identifier put-code="204538" visibility="public" path="/0000-0002-9545-1191/external-identifiers/204538" display-index="0">
                <common:created-date>2014-07-17T13:44:39.499Z</common:created-date>
                <common:last-modified-date>2018-02-05T23:27:36.636Z</common:last-modified-date>
                <common:source>
                    <common:source-client-id>
                        <common:uri>https://orcid.org/client/0000-0002-5982-8983</common:uri>
                        <common:path>0000-0002-5982-8983</common:path>
                        <common:host>orcid.org</common:host>
                    </common:source-client-id>
                    <common:source-name>Scopus - Elsevier</common:source-name>
                </common:source>
                <common:external-id-type>Scopus Author ID</common:external-id-type>
                <common:external-id-value>55790855700</common:external-id-value>
                <common:external-id-url>http://www.scopus.com/inward/authorDetails.url?authorID=55790855700&amp;partnerID=MN8TOARS</common:external-id-url>
                <common:external-id-relationship>self</common:external-id-relationship>
            </external-identifier:external-identifier>
        </external-identifier:external-identifiers>
    </person:person>
    <activities:activities-summary path="/0000-0002-9545-1191/activities">
        <common:last-modified-date>2016-09-10T10:43:01.476Z</common:last-modified-date>
        <activities:distinctions path="/0000-0002-9545-1191/distinctions"/>
        <activities:educations path="/0000-0002-9545-1191/educations">
            <common:last-modified-date>2015-08-28T03:55:52.015Z</common:last-modified-date>
            <activities:affiliation-group>
                <common:last-modified-date>2015-08-28T03:54:27.404Z</common:last-modified-date>
                <common:external-ids/>
                <education:education-summary put-code="741425" display-index="0" path="/0000-0002-9545-1191/education/741425" visibility="public">
                    <common:created-date>2015-02-19T04:15:06.803Z</common:created-date>
                    <common:last-modified-date>2015-08-28T03:54:27.404Z</common:last-modified-date>
                    <common:source>
                        <common:source-orcid>
                            <common:uri>https://orcid.org/0000-0002-9545-1191</common:uri>
                            <common:path>0000-0002-9545-1191</common:path>
                            <common:host>orcid.org</common:host>
                        </common:source-orcid>
                        <common:source-name>Yi-Fong Chen</common:source-name>
                    </common:source>
                    <common:department-name>The Ph.D. Program for Cancer Biology and Drug Discovery</common:department-name>
                    <common:role-title>Doctor of Science (Doctor of Philosophy)</common:role-title>
                    <common:start-date>
                        <common:year>2011</common:year>
                        <common:month>08</common:month>
                        <common:day>01</common:day>
                    </common:start-date>
                    <common:end-date>
                        <common:year>2015</common:year>
                        <common:month>07</common:month>
                        <common:day>31</common:day>
                    </common:end-date>
                    <common:organization>
                        <common:name>China Medical University</common:name>
                        <common:address>
                            <common:city>Taichung</common:city>
                            <common:region>No.91 Hsueh-Shih Road, Taichung, 40402, Taiwan, R.O.C.</common:region>
                            <common:country>TW</common:country>
                        </common:address>
                        <common:disambiguated-organization>
                            <common:disambiguated-organization-identifier>38019</common:disambiguated-organization-identifier>
                            <common:disambiguation-source>RINGGOLD</common:disambiguation-source>
                        </common:disambiguated-organization>
                    </common:organization>
                </education:education-summary>
            </activities:affiliation-group>
            <activities:affiliation-group>
                <common:last-modified-date>2015-08-28T03:52:55.725Z</common:last-modified-date>
                <common:external-ids/>
                <education:education-summary put-code="1132349" display-index="0" path="/0000-0002-9545-1191/education/1132349" visibility="public">
                    <common:created-date>2015-08-28T03:50:42.142Z</common:created-date>
                    <common:last-modified-date>2015-08-28T03:52:55.725Z</common:last-modified-date>
                    <common:source>
                        <common:source-orcid>
                            <common:uri>https://orcid.org/0000-0002-9545-1191</common:uri>
                            <common:path>0000-0002-9545-1191</common:path>
                            <common:host>orcid.org</common:host>
                        </common:source-orcid>
                        <common:source-name>Yi-Fong Chen</common:source-name>
                    </common:source>
                    <common:department-name>School of Pharmacy (Graduate Institute of Pharmaceutical Chemistry)</common:department-name>
                    <common:role-title>Master's Degree</common:role-title>
                    <common:start-date>
                        <common:year>2010</common:year>
                        <common:month>09</common:month>
                    </common:start-date>
                    <common:end-date>
                        <common:year>2011</common:year>
                        <common:month>08</common:month>
                    </common:end-date>
                    <common:organization>
                        <common:name>China Medical University</common:name>
                        <common:address>
                            <common:city>Taichung</common:city>
                            <common:region>No. 91 Hsueh-Shih Road, Taichung 40402, Taiwan, R.O.C.</common:region>
                            <common:country>TW</common:country>
                        </common:address>
                        <common:disambiguated-organization>
                            <common:disambiguated-organization-identifier>38019</common:disambiguated-organization-identifier>
                            <common:disambiguation-source>RINGGOLD</common:disambiguation-source>
                        </common:disambiguated-organization>
                    </common:organization>
                </education:education-summary>
            </activities:affiliation-group>
            <activities:affiliation-group>
                <common:last-modified-date>2015-08-28T03:55:52.015Z</common:last-modified-date>
                <common:external-ids/>
                <education:education-summary put-code="364665" display-index="0" path="/0000-0002-9545-1191/education/364665" visibility="public">
                    <common:created-date>2014-07-17T13:39:52.362Z</common:created-date>
                    <common:last-modified-date>2015-08-28T03:55:52.015Z</common:last-modified-date>
                    <common:source>
                        <common:source-orcid>
                            <common:uri>https://orcid.org/0000-0002-9545-1191</common:uri>
                            <common:path>0000-0002-9545-1191</common:path>
                            <common:host>orcid.org</common:host>
                        </common:source-orcid>
                        <common:source-name>Yi-Fong Chen</common:source-name>
                    </common:source>
                    <common:department-name>Department of Pharmacy</common:department-name>
                    <common:role-title>Bachelor Degree; B.S. (Pharmacist)</common:role-title>
                    <common:start-date>
                        <common:year>2006</common:year>
                        <common:month>08</common:month>
                        <common:day>01</common:day>
                    </common:start-date>
                    <common:end-date>
                        <common:year>2010</common:year>
                        <common:month>07</common:month>
                        <common:day>31</common:day>
                    </common:end-date>
                    <common:organization>
                        <common:name>Chia Nan University of Pharmacy and Science </common:name>
                        <common:address>
                            <common:city>Tainan</common:city>
                            <common:region>60 Erh-Jen Road,Sec. 1, Jen-Te, Tainan 717, Taiwan</common:region>
                            <common:country>TW</common:country>
                        </common:address>
                        <common:disambiguated-organization>
                            <common:disambiguated-organization-identifier>71664</common:disambiguated-organization-identifier>
                            <common:disambiguation-source>RINGGOLD</common:disambiguation-source>
                        </common:disambiguated-organization>
                    </common:organization>
                </education:education-summary>
            </activities:affiliation-group>
        </activities:educations>
        <activities:employments path="/0000-0002-9545-1191/employments"/>
        <activities:fundings path="/0000-0002-9545-1191/fundings"/>
        <activities:invited-positions path="/0000-0002-9545-1191/invited-positions"/>
        <activities:memberships path="/0000-0002-9545-1191/memberships"/>
        <activities:peer-reviews path="/0000-0002-9545-1191/peer-reviews"/>
        <activities:qualifications path="/0000-0002-9545-1191/qualifications"/>
        <activities:research-resources path="/0000-0002-9545-1191/research-resources"/>
        <activities:services path="/0000-0002-9545-1191/services"/>
        <activities:works path="/0000-0002-9545-1191/works">
            <common:last-modified-date>2016-09-10T10:43:01.476Z</common:last-modified-date>
            <activities:group>
                <common:last-modified-date>2015-07-24T13:49:24.511Z</common:last-modified-date>
                <common:external-ids>
                    <common:external-id>
                        <common:external-id-type>doi</common:external-id-type>
                        <common:external-id-value>10.1111/bph.12992</common:external-id-value>
                        <common:external-id-normalized transient="true">10.1111/bph.12992</common:external-id-normalized>
                        <common:external-id-url></common:external-id-url>
                        <common:external-id-relationship>self</common:external-id-relationship>
                    </common:external-id>
                </common:external-ids>
                <work:work-summary put-code="15463795" path="/0000-0002-9545-1191/work/15463795" visibility="public" display-index="0">
                    <common:created-date>2015-02-19T04:20:35.153Z</common:created-date>
                    <common:last-modified-date>2015-07-24T13:49:24.511Z</common:last-modified-date>
                    <common:source>
                        <common:source-orcid>
                            <common:uri>https://orcid.org/0000-0002-9545-1191</common:uri>
                            <common:path>0000-0002-9545-1191</common:path>
                            <common:host>orcid.org</common:host>
                        </common:source-orcid>
                        <common:source-name>Yi-Fong Chen</common:source-name>
                    </common:source>
                    <work:title>
                        <common:title>Synthesis and SAR studies of novel 6,7,8-substituted 4-substituted benzyloxyquinolin-2(1H)-one derivatives for anticancer activity</common:title>
                    </work:title>
                    <common:external-ids>
                        <common:external-id>
                            <common:external-id-type>doi</common:external-id-type>
                            <common:external-id-value>10.1111/bph.12992</common:external-id-value>
                            <common:external-id-normalized transient="true">10.1111/bph.12992</common:external-id-normalized>
                            <common:external-id-url></common:external-id-url>
                            <common:external-id-relationship>self</common:external-id-relationship>
                        </common:external-id>
                    </common:external-ids>
                    <common:url>http://dx.doi.org/10.1111/bph.12992</common:url>
                    <work:type>journal-article</work:type>
                    <common:publication-date>
                        <common:year>2015</common:year>
                    </common:publication-date>
                    <work:journal-title>British Journal of Pharmacology</work:journal-title>
                </work:work-summary>
            </activities:group>
            <activities:group>
                <common:last-modified-date>2016-09-10T10:43:01.476Z</common:last-modified-date>
                <common:external-ids>
                    <common:external-id>
                        <common:external-id-type>doi</common:external-id-type>
                        <common:external-id-value>http://dx.doi.org/10.1016/j.bmcl.2015.07.058</common:external-id-value>
                        <common:external-id-normalized transient="true">10.1016/j.bmcl.2015.07.058</common:external-id-normalized>
                    </common:external-id>
                </common:external-ids>
                <work:work-summary put-code="18120231" path="/0000-0002-9545-1191/work/18120231" visibility="public" display-index="1">
                    <common:created-date>2015-08-28T03:40:35.981Z</common:created-date>
                    <common:last-modified-date>2015-08-28T03:40:35.981Z</common:last-modified-date>
                    <common:source>
                        <common:source-orcid>
                            <common:uri>https://orcid.org/0000-0002-9545-1191</common:uri>
                            <common:path>0000-0002-9545-1191</common:path>
                            <common:host>orcid.org</common:host>
                        </common:source-orcid>
                        <common:source-name>Yi-Fong Chen</common:source-name>
                    </common:source>
                    <work:title>
                        <common:title>Synthesis and biological evaluation of novel 3,9-substituted β-carboline derivatives as anticancer agents </common:title>
                    </work:title>
                    <common:external-ids>
                        <common:external-id>
                            <common:external-id-type>doi</common:external-id-type>
                            <common:external-id-value>http://dx.doi.org/10.1016/j.bmcl.2015.07.058</common:external-id-value>
                            <common:external-id-normalized transient="true">10.1016/j.bmcl.2015.07.058</common:external-id-normalized>
                        </common:external-id>
                    </common:external-ids>
                    <common:url>http://www.sciencedirect.com/science/article/pii/S0960894X15007623</common:url>
                    <work:type>journal-article</work:type>
                    <common:publication-date>
                        <common:year>2015</common:year>
                    </common:publication-date>
                    <work:journal-title>Bioorganic &amp; Medicinal Chemistry Letters </work:journal-title>
                </work:work-summary>
                <work:work-summary put-code="21471295" path="/0000-0002-9545-1191/work/21471295" visibility="public" display-index="0">
                    <common:created-date>2016-01-13T17:14:18.434Z</common:created-date>
                    <common:last-modified-date>2016-09-10T10:43:01.476Z</common:last-modified-date>
                    <common:source>
                        <common:source-client-id>
                            <common:uri>https://orcid.org/client/0000-0001-9884-1913</common:uri>
                            <common:path>0000-0001-9884-1913</common:path>
                            <common:host>orcid.org</common:host>
                        </common:source-client-id>
                        <common:source-name>Crossref</common:source-name>
                    </common:source>
                    <work:title>
                        <common:title>Synthesis and biological evaluation of novel 3,9-substituted β-carboline derivatives as anticancer agents</common:title>
                    </work:title>
                    <common:external-ids>
                        <common:external-id>
                            <common:external-id-type>doi</common:external-id-type>
                            <common:external-id-value>10.1016/j.bmcl.2015.07.058</common:external-id-value>
                            <common:external-id-normalized transient="true">10.1016/j.bmcl.2015.07.058</common:external-id-normalized>
                            <common:external-id-url>http://dx.doi.org/10.1016/j.bmcl.2015.07.058</common:external-id-url>
                            <common:external-id-relationship>self</common:external-id-relationship>
                        </common:external-id>
                    </common:external-ids>
                    <work:type>journal-article</work:type>
                    <common:publication-date>
                        <common:year>2015</common:year>
                        <common:month>09</common:month>
                    </common:publication-date>
                    <work:journal-title>Bioorganic &amp; Medicinal Chemistry Letters</work:journal-title>
                </work:work-summary>
            </activities:group>
            <activities:group>
                <common:last-modified-date>2015-07-22T16:37:43.224Z</common:last-modified-date>
                <common:external-ids>
                    <common:external-id>
                        <common:external-id-type>eid</common:external-id-type>
                        <common:external-id-value>2-s2.0-84881374909</common:external-id-value>
                        <common:external-id-normalized transient="true">2-s2.0-84881374909</common:external-id-normalized>
                        <common:external-id-url></common:external-id-url>
                        <common:external-id-relationship>self</common:external-id-relationship>
                    </common:external-id>
                    <common:external-id>
                        <common:external-id-type>doi</common:external-id-type>
                        <common:external-id-value>10.1016/j.bmc.2013.06.046</common:external-id-value>
                        <common:external-id-normalized transient="true">10.1016/j.bmc.2013.06.046</common:external-id-normalized>
                        <common:external-id-url></common:external-id-url>
                        <common:external-id-relationship>self</common:external-id-relationship>
                    </common:external-id>
                </common:external-ids>
                <work:work-summary put-code="13166164" path="/0000-0002-9545-1191/work/13166164" visibility="public" display-index="0">
                    <common:created-date>2014-07-17T13:44:50.527Z</common:created-date>
                    <common:last-modified-date>2015-07-22T16:37:43.224Z</common:last-modified-date>
                    <common:source>
                        <common:source-client-id>
                            <common:uri>https://orcid.org/client/0000-0002-5982-8983</common:uri>
                            <common:path>0000-0002-5982-8983</common:path>
                            <common:host>orcid.org</common:host>
                        </common:source-client-id>
                        <common:source-name>Scopus - Elsevier</common:source-name>
                    </common:source>
                    <work:title>
                        <common:title>Design and synthesis of 6,7-methylenedioxy-4-substituted phenylquinolin-2(1H)-one derivatives as novel anticancer agents that induce apoptosis with cell cycle arrest at G2/M phase</common:title>
                    </work:title>
                    <common:external-ids>
                        <common:external-id>
                            <common:external-id-type>doi</common:external-id-type>
                            <common:external-id-value>10.1016/j.bmc.2013.06.046</common:external-id-value>
                            <common:external-id-normalized transient="true">10.1016/j.bmc.2013.06.046</common:external-id-normalized>
                            <common:external-id-url></common:external-id-url>
                            <common:external-id-relationship>self</common:external-id-relationship>
                        </common:external-id>
                        <common:external-id>
                            <common:external-id-type>eid</common:external-id-type>
                            <common:external-id-value>2-s2.0-84881374909</common:external-id-value>
                            <common:external-id-normalized transient="true">2-s2.0-84881374909</common:external-id-normalized>
                            <common:external-id-url></common:external-id-url>
                            <common:external-id-relationship>self</common:external-id-relationship>
                        </common:external-id>
                    </common:external-ids>
                    <common:url>http://www.scopus.com/inward/record.url?eid=2-s2.0-84881374909&amp;partnerID=MN8TOARS</common:url>
                    <work:type>journal-article</work:type>
                    <common:publication-date>
                        <common:year>2013</common:year>
                    </common:publication-date>
                </work:work-summary>
            </activities:group>
        </activities:works>
    </activities:activities-summary>
</record:record>
