<?xml version="1.0" encoding="UTF-8" standalone="yes"?>
<record:record xmlns:address="http://www.orcid.org/ns/address" xmlns:email="http://www.orcid.org/ns/email" xmlns:history="http://www.orcid.org/ns/history" xmlns:employment="http://www.orcid.org/ns/employment" xmlns:education="http://www.orcid.org/ns/education" xmlns:other-name="http://www.orcid.org/ns/other-name" xmlns:deprecated="http://www.orcid.org/ns/deprecated" xmlns:funding="http://www.orcid.org/ns/funding" xmlns:research-resource="http://www.orcid.org/ns/research-resource" xmlns:service="http://www.orcid.org/ns/service" xmlns:researcher-url="http://www.orcid.org/ns/researcher-url" xmlns:distinction="http://www.orcid.org/ns/distinction" xmlns:internal="http://www.orcid.org/ns/internal" xmlns:membership="http://www.orcid.org/ns/membership" xmlns:person="http://www.orcid.org/ns/person" xmlns:personal-details="http://www.orcid.org/ns/personal-details" xmlns:bulk="http://www.orcid.org/ns/bulk" xmlns:common="http://www.orcid.org/ns/common" xmlns:record="http://www.orcid.org/ns/record" xmlns:keyword="http://www.orcid.org/ns/keyword" xmlns:activities="http://www.orcid.org/ns/activities" xmlns:qualification="http://www.orcid.org/ns/qualification" xmlns:external-identifier="http://www.orcid.org/ns/external-identifier" xmlns:error="http://www.orcid.org/ns/error" xmlns:preferences="http://www.orcid.org/ns/preferences" xmlns:invited-position="http://www.orcid.org/ns/invited-position" xmlns:work="http://www.orcid.org/ns/work" xmlns:peer-review="http://www.orcid.org/ns/peer-review" path="/0000-0001-5092-2191">
    <common:orcid-identifier>
        <common:uri>https://orcid.org/0000-0001-5092-2191</common:uri>
        <common:path>0000-0001-5092-2191</common:path>
        <common:host>orcid.org</common:host>
    </common:orcid-identifier>
    <preferences:preferences>
        <preferences:locale>en</preferences:locale>
    </preferences:preferences>
    <history:history>
        <history:creation-method>Member-referred</history:creation-method>
        <history:submission-date>2016-01-25T18:55:24.800Z</history:submission-date>
        <common:last-modified-date>2018-09-14T20:11:24.955Z</common:last-modified-date>
        <history:claimed>true</history:claimed>
        <history:verified-email>true</history:verified-email>
        <history:verified-primary-email>true</history:verified-primary-email>
    </history:history>
    <person:person path="/0000-0001-5092-2191/person">
        <common:last-modified-date>2018-02-05T23:27:36.636Z</common:last-modified-date>
        <person:name visibility="public" path="0000-0001-5092-2191">
            <common:created-date>2016-04-15T20:46:50.397Z</common:created-date>
            <common:last-modified-date>2016-04-15T20:46:50.397Z</common:last-modified-date>
            <personal-details:given-names>ADRIANA</personal-details:given-names>
            <personal-details:family-name>GOMEZ-CABRERA</personal-details:family-name>
        </person:name>
        <other-name:other-names path="/0000-0001-5092-2191/other-names"/>
        <researcher-url:researcher-urls path="/0000-0001-5092-2191/researcher-urls">
            <common:last-modified-date>2017-01-31T20:06:02.929Z</common:last-modified-date>
            <researcher-url:researcher-url put-code="1032353" visibility="public" path="/0000-0001-5092-2191/researcher-urls/1032353" display-index="0">
                <common:created-date>2017-01-31T20:06:02.929Z</common:created-date>
                <common:last-modified-date>2017-01-31T20:06:02.929Z</common:last-modified-date>
                <common:source>
                    <common:source-client-id>
                        <common:uri>https://orcid.org/client/0000-0001-6478-3604</common:uri>
                        <common:path>0000-0001-6478-3604</common:path>
                        <common:host>orcid.org</common:host>
                    </common:source-client-id>
                    <common:source-name>Elsevier - Mendeley</common:source-name>
                </common:source>
                <researcher-url:url-name>Mendeley profile</researcher-url:url-name>
                <researcher-url:url>https://www.mendeley.com/profiles/adriana-gomez-cabrera2/</researcher-url:url>
            </researcher-url:researcher-url>
        </researcher-url:researcher-urls>
        <email:emails path="/0000-0001-5092-2191/email"/>
        <address:addresses path="/0000-0001-5092-2191/address"/>
        <keyword:keywords path="/0000-0001-5092-2191/keywords"/>
        <external-identifier:external-identifiers path="/0000-0001-5092-2191/external-identifiers">
            <common:last-modified-date>2018-02-05T23:27:36.636Z</common:last-modified-date>
            <external-identifier:external-identifier put-code="451272" visibility="public" path="/0000-0001-5092-2191/external-identifiers/451272" display-index="0">
                <common:created-date>2016-03-31T16:23:19.731Z</common:created-date>
                <common:last-modified-date>2018-02-05T23:27:36.636Z</common:last-modified-date>
                <common:source>
                    <common:source-client-id>
                        <common:uri>https://orcid.org/client/0000-0002-5982-8983</common:uri>
                        <common:path>0000-0002-5982-8983</common:path>
                        <common:host>orcid.org</common:host>
                    </common:source-client-id>
                    <common:source-name>Scopus - Elsevier</common:source-name>
                </common:source>
                <common:external-id-type>Scopus Author ID</common:external-id-type>
                <common:external-id-value>55502013600</common:external-id-value>
                <common:external-id-url>http://www.scopus.com/inward/authorDetails.url?authorID=55502013600&amp;partnerID=MN8TOARS</common:external-id-url>
                <common:external-id-relationship>self</common:external-id-relationship>
            </external-identifier:external-identifier>
        </external-identifier:external-identifiers>
    </person:person>
    <activities:activities-summary path="/0000-0001-5092-2191/activities">
        <common:last-modified-date>2017-01-31T20:06:02.930Z</common:last-modified-date>
        <activities:distinctions path="/0000-0001-5092-2191/distinctions"/>
        <activities:educations path="/0000-0001-5092-2191/educations"/>
        <activities:employments path="/0000-0001-5092-2191/employments"/>
        <activities:fundings path="/0000-0001-5092-2191/fundings"/>
        <activities:invited-positions path="/0000-0001-5092-2191/invited-positions"/>
        <activities:memberships path="/0000-0001-5092-2191/memberships"/>
        <activities:peer-reviews path="/0000-0001-5092-2191/peer-reviews"/>
        <activities:qualifications path="/0000-0001-5092-2191/qualifications"/>
        <activities:research-resources path="/0000-0001-5092-2191/research-resources"/>
        <activities:services path="/0000-0001-5092-2191/services"/>
        <activities:works path="/0000-0001-5092-2191/works">
            <common:last-modified-date>2017-01-31T20:06:02.930Z</common:last-modified-date>
            <activities:group>
                <common:last-modified-date>2017-01-31T20:06:02.930Z</common:last-modified-date>
                <common:external-ids>
                    <common:external-id>
                        <common:external-id-type>other-id</common:external-id-type>
                        <common:external-id-value>291339265007</common:external-id-value>
                        <common:external-id-normalized transient="true">291339265007</common:external-id-normalized>
                        <common:external-id-relationship>self</common:external-id-relationship>
                    </common:external-id>
                </common:external-ids>
                <work:work-summary put-code="23249984" path="/0000-0001-5092-2191/work/23249984" visibility="public" display-index="0">
                    <common:created-date>2016-03-31T16:24:10.790Z</common:created-date>
                    <common:last-modified-date>2017-01-31T20:06:02.930Z</common:last-modified-date>
                    <common:source>
                        <common:source-client-id>
                            <common:uri>https://orcid.org/client/APP-AWSI2JKPFWG891ZC</common:uri>
                            <common:path>APP-AWSI2JKPFWG891ZC</common:path>
                            <common:host>orcid.org</common:host>
                        </common:source-client-id>
                        <common:source-name>Redalyc</common:source-name>
                    </common:source>
                    <work:title>
                        <common:title>Improving construction material and equipment logistics via simulation</common:title>
                    </work:title>
                    <common:external-ids>
                        <common:external-id>
                            <common:external-id-type>other-id</common:external-id-type>
                            <common:external-id-value>291339265007</common:external-id-value>
                            <common:external-id-normalized transient="true">291339265007</common:external-id-normalized>
                            <common:external-id-relationship>self</common:external-id-relationship>
                        </common:external-id>
                    </common:external-ids>
                    <common:url>http://www.redalyc.org/articulo.oa?id=291339265007</common:url>
                    <work:type>journal-article</work:type>
                    <common:publication-date>
                        <common:year>2015</common:year>
                    </common:publication-date>
                    <work:journal-title>Ingeniería y Competitividad</work:journal-title>
                </work:work-summary>
            </activities:group>
            <activities:group>
                <common:last-modified-date>2017-01-31T20:06:02.930Z</common:last-modified-date>
                <common:external-ids>
                    <common:external-id>
                        <common:external-id-type>other-id</common:external-id-type>
                        <common:external-id-value>83533766008</common:external-id-value>
                        <common:external-id-normalized transient="true">83533766008</common:external-id-normalized>
                        <common:external-id-relationship>self</common:external-id-relationship>
                    </common:external-id>
                </common:external-ids>
                <work:work-summary put-code="23249985" path="/0000-0001-5092-2191/work/23249985" visibility="public" display-index="0">
                    <common:created-date>2016-03-31T16:24:10.794Z</common:created-date>
                    <common:last-modified-date>2017-01-31T20:06:02.930Z</common:last-modified-date>
                    <common:source>
                        <common:source-client-id>
                            <common:uri>https://orcid.org/client/APP-AWSI2JKPFWG891ZC</common:uri>
                            <common:path>APP-AWSI2JKPFWG891ZC</common:path>
                            <common:host>orcid.org</common:host>
                        </common:source-client-id>
                        <common:source-name>Redalyc</common:source-name>
                    </common:source>
                    <work:title>
                        <common:title>Simulación de eventos discretos y líneas de balance, aplicadas al mejoramiento del proceso constructivo de la cimentación de un edificio</common:title>
                    </work:title>
                    <common:external-ids>
                        <common:external-id>
                            <common:external-id-type>other-id</common:external-id-type>
                            <common:external-id-value>83533766008</common:external-id-value>
                            <common:external-id-normalized transient="true">83533766008</common:external-id-normalized>
                            <common:external-id-relationship>self</common:external-id-relationship>
                        </common:external-id>
                    </common:external-ids>
                    <common:url>http://www.redalyc.org/articulo.oa?id=83533766008</common:url>
                    <work:type>journal-article</work:type>
                    <common:publication-date>
                        <common:year>2015</common:year>
                    </common:publication-date>
                    <work:journal-title>Ingeniería y Ciencia</work:journal-title>
                </work:work-summary>
            </activities:group>
            <activities:group>
                <common:last-modified-date>2017-01-31T20:06:02.930Z</common:last-modified-date>
                <common:external-ids>
                    <common:external-id>
                        <common:external-id-type>other-id</common:external-id-type>
                        <common:external-id-value>91132760009</common:external-id-value>
                        <common:external-id-normalized transient="true">91132760009</common:external-id-normalized>
                        <common:external-id-relationship>self</common:external-id-relationship>
                    </common:external-id>
                </common:external-ids>
                <work:work-summary put-code="23249986" path="/0000-0001-5092-2191/work/23249986" visibility="public" display-index="0">
                    <common:created-date>2016-03-31T16:24:10.800Z</common:created-date>
                    <common:last-modified-date>2017-01-31T20:06:02.930Z</common:last-modified-date>
                    <common:source>
                        <common:source-client-id>
                            <common:uri>https://orcid.org/client/APP-AWSI2JKPFWG891ZC</common:uri>
                            <common:path>APP-AWSI2JKPFWG891ZC</common:path>
                            <common:host>orcid.org</common:host>
                        </common:source-client-id>
                        <common:source-name>Redalyc</common:source-name>
                    </common:source>
                    <work:title>
                        <common:title>USO DE LA METODOLOGÍA BRIM (BRIDGE INFORMATION MODELING) COMO HERRAMIENTA PARA LA PLANIFICACIÓN DE LA CONSTRUCCIÓN DE UN PUENTE DE CONCRETO EN COLOMBIA</common:title>
                    </work:title>
                    <common:external-ids>
                        <common:external-id>
                            <common:external-id-type>other-id</common:external-id-type>
                            <common:external-id-value>91132760009</common:external-id-value>
                            <common:external-id-normalized transient="true">91132760009</common:external-id-normalized>
                            <common:external-id-relationship>self</common:external-id-relationship>
                        </common:external-id>
                    </common:external-ids>
                    <common:url>http://www.redalyc.org/articulo.oa?id=91132760009</common:url>
                    <work:type>journal-article</work:type>
                    <common:publication-date>
                        <common:year>2014</common:year>
                    </common:publication-date>
                    <work:journal-title>Ciencia e Ingeniería Neogranadina</work:journal-title>
                </work:work-summary>
            </activities:group>
            <activities:group>
                <common:last-modified-date>2017-01-31T20:06:02.930Z</common:last-modified-date>
                <common:external-ids>
                    <common:external-id>
                        <common:external-id-type>other-id</common:external-id-type>
                        <common:external-id-value>257028384010</common:external-id-value>
                        <common:external-id-normalized transient="true">257028384010</common:external-id-normalized>
                        <common:external-id-relationship>self</common:external-id-relationship>
                    </common:external-id>
                </common:external-ids>
                <work:work-summary put-code="23249983" path="/0000-0001-5092-2191/work/23249983" visibility="public" display-index="0">
                    <common:created-date>2016-03-31T16:24:10.785Z</common:created-date>
                    <common:last-modified-date>2017-01-31T20:06:02.930Z</common:last-modified-date>
                    <common:source>
                        <common:source-client-id>
                            <common:uri>https://orcid.org/client/APP-AWSI2JKPFWG891ZC</common:uri>
                            <common:path>APP-AWSI2JKPFWG891ZC</common:path>
                            <common:host>orcid.org</common:host>
                        </common:source-client-id>
                        <common:source-name>Redalyc</common:source-name>
                    </common:source>
                    <work:title>
                        <common:title>Gestión de residuos de construcción y demolición (RCD) en Bogotá: perspectivas y limitantes</common:title>
                    </work:title>
                    <common:external-ids>
                        <common:external-id>
                            <common:external-id-type>other-id</common:external-id-type>
                            <common:external-id-value>257028384010</common:external-id-value>
                            <common:external-id-normalized transient="true">257028384010</common:external-id-normalized>
                            <common:external-id-relationship>self</common:external-id-relationship>
                        </common:external-id>
                    </common:external-ids>
                    <common:url>http://www.redalyc.org/articulo.oa?id=257028384010</common:url>
                    <work:type>journal-article</work:type>
                    <common:publication-date>
                        <common:year>2013</common:year>
                    </common:publication-date>
                    <work:journal-title>Tecnura</work:journal-title>
                </work:work-summary>
            </activities:group>
            <activities:group>
                <common:last-modified-date>2017-01-31T20:06:02.930Z</common:last-modified-date>
                <common:external-ids>
                    <common:external-id>
                        <common:external-id-type>eid</common:external-id-type>
                        <common:external-id-value>2-s2.0-84870051778</common:external-id-value>
                        <common:external-id-normalized transient="true">2-s2.0-84870051778</common:external-id-normalized>
                        <common:external-id-relationship>self</common:external-id-relationship>
                    </common:external-id>
                </common:external-ids>
                <work:work-summary put-code="23249982" path="/0000-0001-5092-2191/work/23249982" visibility="public" display-index="0">
                    <common:created-date>2016-03-31T16:23:26.268Z</common:created-date>
                    <common:last-modified-date>2017-01-31T20:06:02.930Z</common:last-modified-date>
                    <common:source>
                        <common:source-client-id>
                            <common:uri>https://orcid.org/client/0000-0002-5982-8983</common:uri>
                            <common:path>0000-0002-5982-8983</common:path>
                            <common:host>orcid.org</common:host>
                        </common:source-client-id>
                        <common:source-name>Scopus - Elsevier</common:source-name>
                    </common:source>
                    <work:title>
                        <common:title>Improvement of constructive processes based on a programmable unit for images capture and digital simulation | Mejoramiento de procesos constructivos a partir de un módulo programable para captura de imágenes y simulación digital</common:title>
                    </work:title>
                    <common:external-ids>
                        <common:external-id>
                            <common:external-id-type>eid</common:external-id-type>
                            <common:external-id-value>2-s2.0-84870051778</common:external-id-value>
                            <common:external-id-normalized transient="true">2-s2.0-84870051778</common:external-id-normalized>
                            <common:external-id-relationship>self</common:external-id-relationship>
                        </common:external-id>
                    </common:external-ids>
                    <common:url>http://www.scopus.com/inward/record.url?eid=2-s2.0-84870051778&amp;partnerID=MN8TOARS</common:url>
                    <work:type>journal-article</work:type>
                    <common:publication-date>
                        <common:year>2012</common:year>
                    </common:publication-date>
                    <work:journal-title>Revista Ingenieria de Construccion</work:journal-title>
                </work:work-summary>
            </activities:group>
            <activities:group>
                <common:last-modified-date>2017-01-31T20:06:02.930Z</common:last-modified-date>
                <common:external-ids/>
                <work:work-summary put-code="23250251" path="/0000-0001-5092-2191/work/23250251" visibility="public" display-index="1">
                    <common:created-date>2016-03-31T16:29:57.679Z</common:created-date>
                    <common:last-modified-date>2017-01-31T20:06:02.930Z</common:last-modified-date>
                    <common:source>
                        <common:source-orcid>
                            <common:uri>https://orcid.org/0000-0001-5092-2191</common:uri>
                            <common:path>0000-0001-5092-2191</common:path>
                            <common:host>orcid.org</common:host>
                        </common:source-orcid>
                        <common:source-name>ADRIANA GOMEZ-CABRERA</common:source-name>
                    </common:source>
                    <work:title>
                        <common:title>Estudio de la tecnología de concretos de contracción compensada aplicada a la construcción de pisos industriales</common:title>
                    </work:title>
                    <common:url>http://apps.webofknowledge.com/full_record.do?product=UA&amp;search_mode=GeneralSearch&amp;qid=3&amp;SID=1BklMvjJYrVnk9Hz2wq&amp;page=1&amp;doc=1</common:url>
                    <work:type>journal-article</work:type>
                    <work:journal-title>Obras y Proyectos</work:journal-title>
                </work:work-summary>
            </activities:group>
        </activities:works>
    </activities:activities-summary>
</record:record>
